{
  "obj": {
    "profession": [
      "טכנאי",
      "ספר",
      "אינסטלטור"
    ],
    "titles": [
      "עיר",
      "טל1",
      "טל2",
      "ווטסאפ",
      "אתר1",
      "אתר2",
      "שם",
      "סוג עסק"
    ],
    "list": [
      {
        "title": "קישורית",
        "type": "מורה פרטי למתמטיקה",
        "name": "מני גולן",
        "city": "עפולה",
        "tel1": "0597113600",
        "whatsapp": "0597113600",
        "website1": "https://www.instagram.com/ronenbr60/",
        "comment": "עסק לדוגמה",
        "active": true
      },
      {
        "name": "יהונתן ג'ונסון",
        "title": "מורה לחליל צד",
        "city": "נוף הגליל",
        "type": "מורה לחליל",
        "tel1": "0597113638",
        "comment": "עסק לדוגמה",
        "active": true
      }
    ]
  }
}
